persistencecurves/PC.py
persistencecurves/__init__.py
persistencecurves-0.0.9.dist-info/LICENSE.txt
persistencecurves-0.0.9.dist-info/METADATA
persistencecurves-0.0.9.dist-info/WHEEL
persistencecurves-0.0.9.dist-info/top_level.txt
persistencecurves-0.0.9.dist-info/RECORD
