Metadata-Version: 2.1
Name: persistencecurves
Version: 0.0.9
Summary: A small package created to aid in the calculation of Persistence Curves
Home-page: https://github.com/azlawson/PersistenceCurves
Author: Austin Lawson
Author-email: azlawson@uncg.edu
License: UNKNOWN
Platform: UNKNOWN
Classifier: Programming Language :: Python :: 3
Classifier: License :: OSI Approved :: MIT License
Classifier: Operating System :: OS Independent
Requires-Dist: numpy
Requires-Dist: scipy
Requires-Dist: matplotlib
